[
  {
    "_id": "5e8442eb30063d00292025d9",
    "name": "Owner / Store Manager",
    "description": "",
    "organisationId": "5d318bd14a75dd5ec137494e",
    "nodeId": "5e72a36b4c3e1706b6c594fd",
    "setting": {
      "managementEnrollCustomers": 2,
      "managementEnrollEmployees": 2,
      "managementCashupCashierSelf": 2,
      "managementSetupHardware": 2,
      "managementPricingLevel": 2,
      "managementCashupStore": 2,
      "startNewSalesOrder": 2,
      "finalizeSaleOrder": 2,
      "subtotalSaleOrder": 2,
      "cancelSubtotalSaleOrder": 2,
      "viewSalesOrderHistory": 2,
      "viewAllSalesOrders": 2,
      "accessAllSalesOrders": 2,
      "addPaymentToSalesOrder": 2,
      "removePaymentToSalesOrder": 2,
      "quickPaymentToSalesOrder": 2,
      "salesOrderTip": 2,
      "storeSaleOrder": 2,
      "printSalesOrder": 2,
      "salesOrderNote": 2,
      "salesOrderCustomer": 2,
      "salesOrderSaleName": 2,
      "salesOrderTableNum": 2,
      "salesOrderGuestCount": 2,
      "salesOrderEmployee": 2,
      "tenderCash": 2,
      "tenderCard": 2,
      "tenderCheque": 2,
      "tenderAccounts": 2,
      "tenderNonTurnover": 2,
      "saleOrderDiscount": 2,
      "addItemToSalesOrder": 2,
      "salesOrderItemPriceOverride": 2,
      "salesOrderItemPercentageDiscount": 2,
      "salesOrderItemValueDiscount": 2,
      "removeUncommittedItemsFromSalesOrder": 2,
      "removeCommittedItemsFromSalesOrder": 2,
      "changeOrderItemQty": 2,
      "accessBusyTables": 2,
      "salesOrderNegativeInvoice": 2,
      "salesOrderRecallInvoice": 2,
      "salesOrderType": 2,
      "managementSupportInfo": 2,
      "managementAccessUnity": 1,
      "managementFinancialTotals": 2,
      "showProductInfo": 2,
      "tenderAccountLimitOverride": 2,
      "managementCashupTill": 2,
      "managementCashupCashierOther": 2,
      "managementCashupViewBalanceDetails": 2
    },
    "lastUpdated": 20200414123153,
    "accessRole": [
      "5d318bd14a75dd5ec1374970"
    ]
  },
  {
    "_id": "5e84431b30063d00292025da",
    "name": "Middle Manager",
    "description": "",
    "organisationId": "5d318bd14a75dd5ec137494e",
    "nodeId": "5e72a36b4c3e1706b6c594fd",
    "setting": {
      "managementEnrollCustomers": 1,
      "managementEnrollEmployees": 1,
      "managementCashupCashierSelf": 1,
      "managementSetupHardware": 1,
      "managementPricingLevel": 1,
      "managementCashupStore": 1,
      "startNewSalesOrder": 2,
      "finalizeSaleOrder": 2,
      "subtotalSaleOrder": 2,
      "cancelSubtotalSaleOrder": 2,
      "viewSalesOrderHistory": 2,
      "viewAllSalesOrders": 2,
      "accessAllSalesOrders": 2,
      "addPaymentToSalesOrder": 2,
      "removePaymentToSalesOrder": 2,
      "quickPaymentToSalesOrder": 2,
      "salesOrderTip": 2,
      "storeSaleOrder": 2,
      "printSalesOrder": 2,
      "salesOrderNote": 2,
      "salesOrderCustomer": 2,
      "salesOrderSaleName": 2,
      "salesOrderTableNum": 2,
      "salesOrderGuestCount": 2,
      "salesOrderEmployee": 2,
      "tenderCash": 2,
      "tenderCard": 2,
      "tenderCheque": 2,
      "tenderAccounts": 2,
      "tenderNonTurnover": 2,
      "saleOrderDiscount": 2,
      "addItemToSalesOrder": 2,
      "salesOrderItemPriceOverride": 2,
      "salesOrderItemPercentageDiscount": 2,
      "salesOrderItemValueDiscount": 2,
      "removeUncommittedItemsFromSalesOrder": 2,
      "removeCommittedItemsFromSalesOrder": 2,
      "changeOrderItemQty": 2,
      "accessBusyTables": 2,
      "salesOrderNegativeInvoice": 2,
      "salesOrderRecallInvoice": 2,
      "salesOrderType": 2,
      "managementSupportInfo": 1,
      "managementAccessUnity": 1,
      "managementFinancialTotals": 1,
      "showProductInfo": 2,
      "tenderAccountLimitOverride": 2,
      "managementCashupTill": 1,
      "managementCashupCashierOther": 1,
      "managementCashupViewBalanceDetails": 1
    },
    "lastUpdated": 20200406001345,
    "accessRole": [
      "5d318bd14a75dd5ec1374970"
    ]
  },
  {
    "_id": "5e84432830063d00292025db",
    "name": "Junior Manager",
    "description": "",
    "organisationId": "5d318bd14a75dd5ec137494e",
    "nodeId": "5e72a36b4c3e1706b6c594fd",
    "setting": {
      "managementEnrollCustomers": 0,
      "managementEnrollEmployees": 0,
      "managementCashupCashierSelf": 0,
      "managementSetupHardware": 0,
      "managementPricingLevel": 0,
      "managementCashupStore": 0,
      "startNewSalesOrder": 2,
      "finalizeSaleOrder": 2,
      "subtotalSaleOrder": 2,
      "cancelSubtotalSaleOrder": 2,
      "viewSalesOrderHistory": 2,
      "viewAllSalesOrders": 2,
      "accessAllSalesOrders": 2,
      "addPaymentToSalesOrder": 2,
      "removePaymentToSalesOrder": 2,
      "quickPaymentToSalesOrder": 2,
      "salesOrderTip": 2,
      "storeSaleOrder": 2,
      "printSalesOrder": 2,
      "salesOrderNote": 2,
      "salesOrderCustomer": 2,
      "salesOrderSaleName": 2,
      "salesOrderTableNum": 2,
      "salesOrderGuestCount": 2,
      "salesOrderEmployee": 2,
      "tenderCash": 2,
      "tenderCard": 2,
      "tenderCheque": 2,
      "tenderAccounts": 2,
      "tenderNonTurnover": 2,
      "saleOrderDiscount": 2,
      "addItemToSalesOrder": 2,
      "salesOrderItemPriceOverride": 2,
      "salesOrderItemPercentageDiscount": 2,
      "salesOrderItemValueDiscount": 2,
      "removeUncommittedItemsFromSalesOrder": 2,
      "removeCommittedItemsFromSalesOrder": 2,
      "changeOrderItemQty": 2,
      "accessBusyTables": 2,
      "salesOrderNegativeInvoice": 2,
      "salesOrderRecallInvoice": 2,
      "salesOrderType": 2,
      "managementSupportInfo": 0,
      "managementAccessUnity": 0,
      "managementFinancialTotals": 0,
      "showProductInfo": 2,
      "tenderAccountLimitOverride": 2,
      "managementCashupTill": 0,
      "managementCashupCashierOther": 0,
      "managementCashupViewBalanceDetails": 0
    },
    "lastUpdated": 20200407234815,
    "accessRole": [
      "5dd28b200d3096030c742d2a",
      "5d318bd14a75dd5ec1374970"
    ]
  },
  {
    "_id": "5e84433530063d00292025dc",
    "name": "Barman",
    "description": "",
    "organisationId": "5d318bd14a75dd5ec137494e",
    "nodeId": "5e72a36b4c3e1706b6c594fd",
    "setting": {
      "managementEnrollCustomers": 0,
      "managementEnrollEmployees": 0,
      "managementCashupCashierSelf": 0,
      "managementSetupHardware": 0,
      "managementPricingLevel": 0,
      "managementCashupStore": 0,
      "startNewSalesOrder": 0,
      "finalizeSaleOrder": 0,
      "subtotalSaleOrder": 0,
      "cancelSubtotalSaleOrder": 0,
      "viewSalesOrderHistory": 0,
      "viewAllSalesOrders": 0,
      "accessAllSalesOrders": 0,
      "addPaymentToSalesOrder": 0,
      "removePaymentToSalesOrder": 0,
      "quickPaymentToSalesOrder": 0,
      "salesOrderTip": 0,
      "storeSaleOrder": 0,
      "printSalesOrder": 0,
      "salesOrderNote": 0,
      "salesOrderCustomer": 0,
      "salesOrderSaleName": 0,
      "salesOrderTableNum": 0,
      "salesOrderGuestCount": 0,
      "salesOrderEmployee": 0,
      "tenderCash": 2,
      "tenderCard": 2,
      "tenderCheque": 2,
      "tenderAccounts": 2,
      "tenderNonTurnover": 2,
      "saleOrderDiscount": 0,
      "addItemToSalesOrder": 2,
      "salesOrderItemPriceOverride": 2,
      "salesOrderItemPercentageDiscount": 2,
      "salesOrderItemValueDiscount": 2,
      "removeUncommittedItemsFromSalesOrder": 2,
      "removeCommittedItemsFromSalesOrder": 2,
      "changeOrderItemQty": 2,
      "accessBusyTables": 0,
      "salesOrderNegativeInvoice": 0,
      "salesOrderRecallInvoice": 0,
      "salesOrderType": 0,
      "managementSupportInfo": 0,
      "managementAccessUnity": 0,
      "managementFinancialTotals": 0,
      "showProductInfo": 2,
      "tenderAccountLimitOverride": 2,
      "managementCashupTill": 0,
      "managementCashupCashierOther": 0,
      "managementCashupViewBalanceDetails": 0
    },
    "lastUpdated": 20200406001705,
    "accessRole": [
      "5dd28b200d3096030c742d2a",
      "5d318bd14a75dd5ec1374970"
    ]
  },
  {
    "_id": "5e84433e30063d00292025dd",
    "name": "Kitchen Staff",
    "description": "",
    "organisationId": "5d318bd14a75dd5ec137494e",
    "nodeId": "5e72a36b4c3e1706b6c594fd",
    "setting": {
      "managementEnrollCustomers": 0,
      "managementEnrollEmployees": 0,
      "managementCashupCashierSelf": 0,
      "managementSetupHardware": 0,
      "managementPricingLevel": 0,
      "managementCashupStore": 0,
      "startNewSalesOrder": 0,
      "finalizeSaleOrder": 0,
      "subtotalSaleOrder": 0,
      "cancelSubtotalSaleOrder": 0,
      "viewSalesOrderHistory": 0,
      "viewAllSalesOrders": 0,
      "accessAllSalesOrders": 0,
      "addPaymentToSalesOrder": 0,
      "removePaymentToSalesOrder": 0,
      "quickPaymentToSalesOrder": 0,
      "salesOrderTip": 0,
      "storeSaleOrder": 0,
      "printSalesOrder": 0,
      "salesOrderNote": 0,
      "salesOrderCustomer": 0,
      "salesOrderSaleName": 0,
      "salesOrderTableNum": 0,
      "salesOrderGuestCount": 0,
      "salesOrderEmployee": 0,
      "tenderCash": 0,
      "tenderCard": 0,
      "tenderCheque": 0,
      "tenderAccounts": 0,
      "tenderNonTurnover": 0,
      "saleOrderDiscount": 0,
      "addItemToSalesOrder": 0,
      "salesOrderItemPriceOverride": 0,
      "salesOrderItemPercentageDiscount": 0,
      "salesOrderItemValueDiscount": 0,
      "removeUncommittedItemsFromSalesOrder": 0,
      "removeCommittedItemsFromSalesOrder": 0,
      "changeOrderItemQty": 0,
      "accessBusyTables": 0,
      "salesOrderNegativeInvoice": 0,
      "salesOrderRecallInvoice": 0,
      "salesOrderType": 0,
      "managementSupportInfo": 0,
      "managementAccessUnity": 0,
      "managementFinancialTotals": 0,
      "showProductInfo": 0,
      "tenderAccountLimitOverride": 0,
      "managementCashupTill": 0,
      "managementCashupCashierOther": 0,
      "managementCashupViewBalanceDetails": 0
    },
    "lastUpdated": 20200406001921,
    "accessRole": [
      "5dd28b200d3096030c742d2a",
      "5d318bd14a75dd5ec1374970"
    ]
  },
  {
    "_id": "5e84435730063d00292025de",
    "name": "Waiter / Service Staff",
    "description": "",
    "organisationId": "5d318bd14a75dd5ec137494e",
    "nodeId": "5e72a36b4c3e1706b6c594fd",
    "setting": {
      "managementEnrollCustomers": 0,
      "managementEnrollEmployees": 1,
      "managementCashupCashierSelf": 1,
      "managementSetupHardware": 1,
      "managementPricingLevel": 1,
      "managementCashupStore": 1,
      "startNewSalesOrder": 2,
      "finalizeSaleOrder": 2,
      "subtotalSaleOrder": 2,
      "cancelSubtotalSaleOrder": 2,
      "viewSalesOrderHistory": 2,
      "viewAllSalesOrders": 2,
      "accessAllSalesOrders": 2,
      "addPaymentToSalesOrder": 2,
      "removePaymentToSalesOrder": 1,
      "quickPaymentToSalesOrder": 2,
      "salesOrderTip": 2,
      "storeSaleOrder": 2,
      "printSalesOrder": 2,
      "salesOrderNote": 2,
      "salesOrderCustomer": 2,
      "salesOrderSaleName": 2,
      "salesOrderTableNum": 2,
      "salesOrderGuestCount": 2,
      "salesOrderEmployee": 2,
      "tenderCash": 1,
      "tenderCard": 1,
      "tenderCheque": 1,
      "tenderAccounts": 1,
      "tenderNonTurnover": 1,
      "saleOrderDiscount": 1,
      "addItemToSalesOrder": 2,
      "salesOrderItemPriceOverride": 2,
      "salesOrderItemPercentageDiscount": 2,
      "salesOrderItemValueDiscount": 2,
      "removeUncommittedItemsFromSalesOrder": 2,
      "removeCommittedItemsFromSalesOrder": 2,
      "changeOrderItemQty": 2,
      "accessBusyTables": 2,
      "salesOrderNegativeInvoice": 2,
      "salesOrderRecallInvoice": 2,
      "salesOrderType": 2,
      "managementSupportInfo": 1,
      "managementAccessUnity": 1,
      "managementFinancialTotals": 2,
      "showProductInfo": 2,
      "tenderAccountLimitOverride": 1,
      "managementCashupTill": 1,
      "managementCashupCashierOther": 1,
      "managementCashupViewBalanceDetails": 1
    },
    "lastUpdated": 20200414123127,
    "accessRole": [
      "5dd28b200d3096030c742d2a",
      "5d318bd14a75dd5ec1374970"
    ],
    "isDeleted": false,
    "partial": true
  }
]